{
  "version": "1.0",
  "contributionName": "Lyngesen24",
  "instanceName": "Lyngesen24-msp-2-100|100-uu-2_2",
  "objectives": 2,
  "objectiveType": ["int", "int"],
  "comments": "The nondominated sum for the MSP (points not stored for large Yn sizes)",
  "direction": ["min", "min"],
  "optimal": true,
  "valid": true,
  "card": 364,
  "suppCard": 3,
  "extCard": 3,
  "points": [
    {
      "z1": 32,
      "z2": 20000,
      "type": "se"
    },
    {
      "z1": 124,
      "z2": 19999,
      "type": "us"
    },
    {
      "z1": 211,
      "z2": 19998,
      "type": "us"
    },
    {
      "z1": 319,
      "z2": 19995,
      "type": "us"
    },
    {
      "z1": 419,
      "z2": 19992,
      "type": "us"
    },
    {
      "z1": 469,
      "z2": 19990,
      "type": "us"
    },
    {
      "z1": 484,
      "z2": 19989,
      "type": "us"
    },
    {
      "z1": 555,
      "z2": 19985,
      "type": "us"
    },
    {
      "z1": 647,
      "z2": 19984,
      "type": "us"
    },
    {
      "z1": 734,
      "z2": 19983,
      "type": "us"
    },
    {
      "z1": 742,
      "z2": 19974,
      "type": "us"
    },
    {
      "z1": 822,
      "z2": 19968,
      "type": "us"
    },
    {
      "z1": 880,
      "z2": 19962,
      "type": "us"
    },
    {
      "z1": 972,
      "z2": 19961,
      "type": "us"
    },
    {
      "z1": 1017,
      "z2": 19950,
      "type": "us"
    },
    {
      "z1": 1044,
      "z2": 19947,
      "type": "us"
    },
    {
      "z1": 1087,
      "z2": 19942,
      "type": "us"
    },
    {
      "z1": 1129,
      "z2": 19938,
      "type": "us"
    },
    {
      "z1": 1183,
      "z2": 19931,
      "type": "us"
    },
    {
      "z1": 1237,
      "z2": 19925,
      "type": "us"
    },
    {
      "z1": 1329,
      "z2": 19924,
      "type": "us"
    },
    {
      "z1": 1343,
      "z2": 19912,
      "type": "us"
    },
    {
      "z1": 1357,
      "z2": 19910,
      "type": "us"
    },
    {
      "z1": 1417,
      "z2": 19902,
      "type": "us"
    },
    {
      "z1": 1493,
      "z2": 19890,
      "type": "us"
    },
    {
      "z1": 1512,
      "z2": 19887,
      "type": "us"
    },
    {
      "z1": 1600,
      "z2": 19874,
      "type": "us"
    },
    {
      "z1": 1605,
      "z2": 19873,
      "type": "us"
    },
    {
      "z1": 1619,
      "z2": 19871,
      "type": "us"
    },
    {
      "z1": 1662,
      "z2": 19863,
      "type": "us"
    },
    {
      "z1": 1692,
      "z2": 19858,
      "type": "us"
    },
    {
      "z1": 1710,
      "z2": 19855,
      "type": "us"
    },
    {
      "z1": 1802,
      "z2": 19854,
      "type": "us"
    },
    {
      "z1": 1889,
      "z2": 19853,
      "type": "us"
    },
    {
      "z1": 1997,
      "z2": 19850,
      "type": "us"
    },
    {
      "z1": 2002,
      "z2": 19800,
      "type": "us"
    },
    {
      "z1": 2008,
      "z2": 19799,
      "type": "us"
    },
    {
      "z1": 2033,
      "z2": 19794,
      "type": "us"
    },
    {
      "z1": 2125,
      "z2": 19793,
      "type": "us"
    },
    {
      "z1": 2178,
      "z2": 19764,
      "type": "us"
    },
    {
      "z1": 2308,
      "z2": 19763,
      "type": "us"
    },
    {
      "z1": 2329,
      "z2": 19728,
      "type": "us"
    },
    {
      "z1": 2421,
      "z2": 19727,
      "type": "us"
    },
    {
      "z1": 2508,
      "z2": 19726,
      "type": "us"
    },
    {
      "z1": 2511,
      "z2": 19684,
      "type": "us"
    },
    {
      "z1": 2628,
      "z2": 19653,
      "type": "us"
    },
    {
      "z1": 2645,
      "z2": 19648,
      "type": "us"
    },
    {
      "z1": 2737,
      "z2": 19647,
      "type": "us"
    },
    {
      "z1": 2812,
      "z2": 19602,
      "type": "us"
    },
    {
      "z1": 2868,
      "z2": 19585,
      "type": "us"
    },
    {
      "z1": 2880,
      "z2": 19582,
      "type": "us"
    },
    {
      "z1": 3010,
      "z2": 19581,
      "type": "us"
    },
    {
      "z1": 3093,
      "z2": 19514,
      "type": "us"
    },
    {
      "z1": 3185,
      "z2": 19513,
      "type": "us"
    },
    {
      "z1": 3195,
      "z2": 19482,
      "type": "us"
    },
    {
      "z1": 3272,
      "z2": 19454,
      "type": "us"
    },
    {
      "z1": 3301,
      "z2": 19446,
      "type": "us"
    },
    {
      "z1": 3323,
      "z2": 19438,
      "type": "us"
    },
    {
      "z1": 3341,
      "z2": 19430,
      "type": "us"
    },
    {
      "z1": 3433,
      "z2": 19429,
      "type": "us"
    },
    {
      "z1": 3475,
      "z2": 19382,
      "type": "us"
    },
    {
      "z1": 3567,
      "z2": 19381,
      "type": "us"
    },
    {
      "z1": 3620,
      "z2": 19327,
      "type": "us"
    },
    {
      "z1": 3656,
      "z2": 19315,
      "type": "us"
    },
    {
      "z1": 3786,
      "z2": 19314,
      "type": "us"
    },
    {
      "z1": 3824,
      "z2": 19247,
      "type": "us"
    },
    {
      "z1": 3847,
      "z2": 19236,
      "type": "us"
    },
    {
      "z1": 3939,
      "z2": 19235,
      "type": "us"
    },
    {
      "z1": 4007,
      "z2": 19168,
      "type": "us"
    },
    {
      "z1": 4092,
      "z2": 19131,
      "type": "us"
    },
    {
      "z1": 4184,
      "z2": 19130,
      "type": "us"
    },
    {
      "z1": 4208,
      "z2": 19080,
      "type": "us"
    },
    {
      "z1": 4308,
      "z2": 19033,
      "type": "us"
    },
    {
      "z1": 4331,
      "z2": 19020,
      "type": "us"
    },
    {
      "z1": 4377,
      "z2": 18998,
      "type": "us"
    },
    {
      "z1": 4382,
      "z2": 18995,
      "type": "us"
    },
    {
      "z1": 4385,
      "z2": 18994,
      "type": "us"
    },
    {
      "z1": 4433,
      "z2": 18972,
      "type": "us"
    },
    {
      "z1": 4512,
      "z2": 18931,
      "type": "us"
    },
    {
      "z1": 4593,
      "z2": 18890,
      "type": "us"
    },
    {
      "z1": 4685,
      "z2": 18889,
      "type": "us"
    },
    {
      "z1": 4772,
      "z2": 18888,
      "type": "us"
    },
    {
      "z1": 4825,
      "z2": 18769,
      "type": "us"
    },
    {
      "z1": 4846,
      "z2": 18755,
      "type": "us"
    },
    {
      "z1": 4927,
      "z2": 18712,
      "type": "us"
    },
    {
      "z1": 4931,
      "z2": 18710,
      "type": "us"
    },
    {
      "z1": 4946,
      "z2": 18699,
      "type": "us"
    },
    {
      "z1": 4962,
      "z2": 18692,
      "type": "us"
    },
    {
      "z1": 4966,
      "z2": 18690,
      "type": "us"
    },
    {
      "z1": 5063,
      "z2": 18632,
      "type": "us"
    },
    {
      "z1": 5100,
      "z2": 18610,
      "type": "us"
    },
    {
      "z1": 5125,
      "z2": 18595,
      "type": "us"
    },
    {
      "z1": 5129,
      "z2": 18593,
      "type": "us"
    },
    {
      "z1": 5145,
      "z2": 18586,
      "type": "us"
    },
    {
      "z1": 5268,
      "z2": 18511,
      "type": "us"
    },
    {
      "z1": 5338,
      "z2": 18465,
      "type": "us"
    },
    {
      "z1": 5430,
      "z2": 18464,
      "type": "us"
    },
    {
      "z1": 5478,
      "z2": 18375,
      "type": "us"
    },
    {
      "z1": 5485,
      "z2": 18374,
      "type": "us"
    },
    {
      "z1": 5529,
      "z2": 18344,
      "type": "us"
    },
    {
      "z1": 5532,
      "z2": 18340,
      "type": "us"
    },
    {
      "z1": 5549,
      "z2": 18329,
      "type": "us"
    },
    {
      "z1": 5577,
      "z2": 18313,
      "type": "us"
    },
    {
      "z1": 5627,
      "z2": 18279,
      "type": "us"
    },
    {
      "z1": 5757,
      "z2": 18278,
      "type": "us"
    },
    {
      "z1": 5886,
      "z2": 18094,
      "type": "us"
    },
    {
      "z1": 5954,
      "z2": 18044,
      "type": "us"
    },
    {
      "z1": 5961,
      "z2": 18042,
      "type": "us"
    },
    {
      "z1": 6014,
      "z2": 18003,
      "type": "us"
    },
    {
      "z1": 6038,
      "z2": 17982,
      "type": "us"
    },
    {
      "z1": 6047,
      "z2": 17978,
      "type": "us"
    },
    {
      "z1": 6060,
      "z2": 17968,
      "type": "us"
    },
    {
      "z1": 6148,
      "z2": 17898,
      "type": "us"
    },
    {
      "z1": 6240,
      "z2": 17897,
      "type": "us"
    },
    {
      "z1": 6327,
      "z2": 17896,
      "type": "us"
    },
    {
      "z1": 6366,
      "z2": 17727,
      "type": "us"
    },
    {
      "z1": 6432,
      "z2": 17669,
      "type": "us"
    },
    {
      "z1": 6474,
      "z2": 17636,
      "type": "us"
    },
    {
      "z1": 6511,
      "z2": 17602,
      "type": "us"
    },
    {
      "z1": 6544,
      "z2": 17574,
      "type": "us"
    },
    {
      "z1": 6598,
      "z2": 17527,
      "type": "us"
    },
    {
      "z1": 6603,
      "z2": 17525,
      "type": "us"
    },
    {
      "z1": 6682,
      "z2": 17456,
      "type": "us"
    },
    {
      "z1": 6688,
      "z2": 17447,
      "type": "us"
    },
    {
      "z1": 6780,
      "z2": 17446,
      "type": "us"
    },
    {
      "z1": 6827,
      "z2": 17320,
      "type": "us"
    },
    {
      "z1": 6876,
      "z2": 17278,
      "type": "us"
    },
    {
      "z1": 6970,
      "z2": 17184,
      "type": "us"
    },
    {
      "z1": 7062,
      "z2": 17183,
      "type": "us"
    },
    {
      "z1": 7121,
      "z2": 17035,
      "type": "us"
    },
    {
      "z1": 7141,
      "z2": 17019,
      "type": "us"
    },
    {
      "z1": 7146,
      "z2": 17010,
      "type": "us"
    },
    {
      "z1": 7238,
      "z2": 17009,
      "type": "us"
    },
    {
      "z1": 7268,
      "z2": 16887,
      "type": "us"
    },
    {
      "z1": 7308,
      "z2": 16845,
      "type": "us"
    },
    {
      "z1": 7352,
      "z2": 16793,
      "type": "us"
    },
    {
      "z1": 7429,
      "z2": 16710,
      "type": "us"
    },
    {
      "z1": 7490,
      "z2": 16642,
      "type": "us"
    },
    {
      "z1": 7521,
      "z2": 16607,
      "type": "us"
    },
    {
      "z1": 7613,
      "z2": 16606,
      "type": "us"
    },
    {
      "z1": 7631,
      "z2": 16479,
      "type": "us"
    },
    {
      "z1": 7636,
      "z2": 16478,
      "type": "us"
    },
    {
      "z1": 7727,
      "z2": 16369,
      "type": "us"
    },
    {
      "z1": 7753,
      "z2": 16333,
      "type": "us"
    },
    {
      "z1": 7781,
      "z2": 16298,
      "type": "us"
    },
    {
      "z1": 7807,
      "z2": 16266,
      "type": "us"
    },
    {
      "z1": 7820,
      "z2": 16255,
      "type": "us"
    },
    {
      "z1": 7833,
      "z2": 16234,
      "type": "us"
    },
    {
      "z1": 7861,
      "z2": 16204,
      "type": "us"
    },
    {
      "z1": 7877,
      "z2": 16183,
      "type": "us"
    },
    {
      "z1": 7938,
      "z2": 16100,
      "type": "us"
    },
    {
      "z1": 8021,
      "z2": 15995,
      "type": "us"
    },
    {
      "z1": 8106,
      "z2": 15876,
      "type": "us"
    },
    {
      "z1": 8198,
      "z2": 15875,
      "type": "us"
    },
    {
      "z1": 8226,
      "z2": 15712,
      "type": "us"
    },
    {
      "z1": 8250,
      "z2": 15671,
      "type": "us"
    },
    {
      "z1": 8300,
      "z2": 15599,
      "type": "us"
    },
    {
      "z1": 8322,
      "z2": 15571,
      "type": "us"
    },
    {
      "z1": 8371,
      "z2": 15498,
      "type": "us"
    },
    {
      "z1": 8381,
      "z2": 15476,
      "type": "us"
    },
    {
      "z1": 8416,
      "z2": 15429,
      "type": "us"
    },
    {
      "z1": 8447,
      "z2": 15374,
      "type": "us"
    },
    {
      "z1": 8493,
      "z2": 15301,
      "type": "us"
    },
    {
      "z1": 8516,
      "z2": 15264,
      "type": "us"
    },
    {
      "z1": 8591,
      "z2": 15149,
      "type": "us"
    },
    {
      "z1": 8682,
      "z2": 14994,
      "type": "us"
    },
    {
      "z1": 8688,
      "z2": 14976,
      "type": "us"
    },
    {
      "z1": 8706,
      "z2": 14945,
      "type": "us"
    },
    {
      "z1": 8739,
      "z2": 14894,
      "type": "us"
    },
    {
      "z1": 8779,
      "z2": 14821,
      "type": "us"
    },
    {
      "z1": 8781,
      "z2": 14818,
      "type": "us"
    },
    {
      "z1": 8792,
      "z2": 14797,
      "type": "us"
    },
    {
      "z1": 8827,
      "z2": 14733,
      "type": "us"
    },
    {
      "z1": 8957,
      "z2": 14732,
      "type": "us"
    },
    {
      "z1": 9094,
      "z2": 14198,
      "type": "us"
    },
    {
      "z1": 9114,
      "z2": 14146,
      "type": "us"
    },
    {
      "z1": 9119,
      "z2": 14143,
      "type": "us"
    },
    {
      "z1": 9163,
      "z2": 14038,
      "type": "us"
    },
    {
      "z1": 9167,
      "z2": 14028,
      "type": "us"
    },
    {
      "z1": 9182,
      "z2": 14004,
      "type": "us"
    },
    {
      "z1": 9194,
      "z2": 13966,
      "type": "us"
    },
    {
      "z1": 9259,
      "z2": 13821,
      "type": "us"
    },
    {
      "z1": 9305,
      "z2": 13707,
      "type": "us"
    },
    {
      "z1": 9310,
      "z2": 13687,
      "type": "us"
    },
    {
      "z1": 9388,
      "z2": 13493,
      "type": "us"
    },
    {
      "z1": 9423,
      "z2": 13397,
      "type": "us"
    },
    {
      "z1": 9429,
      "z2": 13371,
      "type": "us"
    },
    {
      "z1": 9469,
      "z2": 13256,
      "type": "us"
    },
    {
      "z1": 9516,
      "z2": 13127,
      "type": "us"
    },
    {
      "z1": 9542,
      "z2": 13048,
      "type": "us"
    },
    {
      "z1": 9549,
      "z2": 13027,
      "type": "us"
    },
    {
      "z1": 9563,
      "z2": 12969,
      "type": "us"
    },
    {
      "z1": 9575,
      "z2": 12944,
      "type": "us"
    },
    {
      "z1": 9581,
      "z2": 12922,
      "type": "us"
    },
    {
      "z1": 9612,
      "z2": 12805,
      "type": "us"
    },
    {
      "z1": 9646,
      "z2": 12704,
      "type": "us"
    },
    {
      "z1": 9648,
      "z2": 12696,
      "type": "us"
    },
    {
      "z1": 9666,
      "z2": 12613,
      "type": "us"
    },
    {
      "z1": 9731,
      "z2": 12364,
      "type": "us"
    },
    {
      "z1": 9767,
      "z2": 12228,
      "type": "us"
    },
    {
      "z1": 9785,
      "z2": 12128,
      "type": "us"
    },
    {
      "z1": 9799,
      "z2": 12079,
      "type": "us"
    },
    {
      "z1": 9816,
      "z2": 11982,
      "type": "us"
    },
    {
      "z1": 9888,
      "z2": 11581,
      "type": "us"
    },
    {
      "z1": 9889,
      "z2": 11574,
      "type": "us"
    },
    {
      "z1": 9914,
      "z2": 11413,
      "type": "us"
    },
    {
      "z1": 9958,
      "z2": 11098,
      "type": "us"
    },
    {
      "z1": 9962,
      "z2": 11016,
      "type": "us"
    },
    {
      "z1": 9968,
      "z2": 11001,
      "type": "us"
    },
    {
      "z1": 9978,
      "z2": 10842,
      "type": "us"
    },
    {
      "z1": 9987,
      "z2": 10735,
      "type": "us"
    },
    {
      "z1": 9991,
      "z2": 10728,
      "type": "us"
    },
    {
      "z1": 9994,
      "z2": 10632,
      "type": "us"
    },
    {
      "z1": 9999,
      "z2": 10546,
      "type": "us"
    },
    {
      "z1": 10001,
      "z2": 10504,
      "type": "us"
    },
    {
      "z1": 10005,
      "z2": 10501,
      "type": "us"
    },
    {
      "z1": 10006,
      "z2": 10481,
      "type": "us"
    },
    {
      "z1": 10007,
      "z2": 10467,
      "type": "us"
    },
    {
      "z1": 10010,
      "z2": 10291,
      "type": "us"
    },
    {
      "z1": 10012,
      "z2": 10179,
      "type": "us"
    },
    {
      "z1": 10013,
      "z2": 10149,
      "type": "us"
    },
    {
      "z1": 10018,
      "z2": 10023,
      "type": "se"
    },
    {
      "z1": 10148,
      "z2": 10022,
      "type": "us"
    },
    {
      "z1": 10541,
      "z2": 10008,
      "type": "us"
    },
    {
      "z1": 10728,
      "z2": 9997,
      "type": "us"
    },
    {
      "z1": 10866,
      "z2": 9985,
      "type": "us"
    },
    {
      "z1": 11073,
      "z2": 9965,
      "type": "us"
    },
    {
      "z1": 11169,
      "z2": 9954,
      "type": "us"
    },
    {
      "z1": 11223,
      "z2": 9948,
      "type": "us"
    },
    {
      "z1": 11479,
      "z2": 9913,
      "type": "us"
    },
    {
      "z1": 11498,
      "z2": 9910,
      "type": "us"
    },
    {
      "z1": 11591,
      "z2": 9896,
      "type": "us"
    },
    {
      "z1": 11648,
      "z2": 9886,
      "type": "us"
    },
    {
      "z1": 11678,
      "z2": 9881,
      "type": "us"
    },
    {
      "z1": 11696,
      "z2": 9878,
      "type": "us"
    },
    {
      "z1": 11988,
      "z2": 9823,
      "type": "us"
    },
    {
      "z1": 11994,
      "z2": 9822,
      "type": "us"
    },
    {
      "z1": 12019,
      "z2": 9817,
      "type": "us"
    },
    {
      "z1": 12315,
      "z2": 9751,
      "type": "us"
    },
    {
      "z1": 12631,
      "z2": 9671,
      "type": "us"
    },
    {
      "z1": 13079,
      "z2": 9537,
      "type": "us"
    },
    {
      "z1": 13258,
      "z2": 9477,
      "type": "us"
    },
    {
      "z1": 13327,
      "z2": 9453,
      "type": "us"
    },
    {
      "z1": 13461,
      "z2": 9405,
      "type": "us"
    },
    {
      "z1": 13606,
      "z2": 9350,
      "type": "us"
    },
    {
      "z1": 13833,
      "z2": 9259,
      "type": "us"
    },
    {
      "z1": 13993,
      "z2": 9191,
      "type": "us"
    },
    {
      "z1": 14078,
      "z2": 9154,
      "type": "us"
    },
    {
      "z1": 14317,
      "z2": 9043,
      "type": "us"
    },
    {
      "z1": 14363,
      "z2": 9021,
      "type": "us"
    },
    {
      "z1": 14368,
      "z2": 9018,
      "type": "us"
    },
    {
      "z1": 14371,
      "z2": 9017,
      "type": "us"
    },
    {
      "z1": 14498,
      "z2": 8954,
      "type": "us"
    },
    {
      "z1": 14579,
      "z2": 8913,
      "type": "us"
    },
    {
      "z1": 14832,
      "z2": 8778,
      "type": "us"
    },
    {
      "z1": 14932,
      "z2": 8722,
      "type": "us"
    },
    {
      "z1": 15049,
      "z2": 8655,
      "type": "us"
    },
    {
      "z1": 15086,
      "z2": 8633,
      "type": "us"
    },
    {
      "z1": 15111,
      "z2": 8618,
      "type": "us"
    },
    {
      "z1": 15115,
      "z2": 8616,
      "type": "us"
    },
    {
      "z1": 15324,
      "z2": 8488,
      "type": "us"
    },
    {
      "z1": 15464,
      "z2": 8398,
      "type": "us"
    },
    {
      "z1": 15518,
      "z2": 8363,
      "type": "us"
    },
    {
      "z1": 15535,
      "z2": 8352,
      "type": "us"
    },
    {
      "z1": 15872,
      "z2": 8117,
      "type": "us"
    },
    {
      "z1": 15940,
      "z2": 8067,
      "type": "us"
    },
    {
      "z1": 16024,
      "z2": 8005,
      "type": "us"
    },
    {
      "z1": 16134,
      "z2": 7921,
      "type": "us"
    },
    {
      "z1": 16346,
      "z2": 7906,
      "type": "us"
    },
    {
      "z1": 16347,
      "z2": 7876,
      "type": "us"
    },
    {
      "z1": 16418,
      "z2": 7692,
      "type": "us"
    },
    {
      "z1": 16497,
      "z2": 7625,
      "type": "us"
    },
    {
      "z1": 16530,
      "z2": 7597,
      "type": "us"
    },
    {
      "z1": 16584,
      "z2": 7550,
      "type": "us"
    },
    {
      "z1": 16674,
      "z2": 7470,
      "type": "us"
    },
    {
      "z1": 16813,
      "z2": 7343,
      "type": "us"
    },
    {
      "z1": 16956,
      "z2": 7207,
      "type": "us"
    },
    {
      "z1": 17107,
      "z2": 7058,
      "type": "us"
    },
    {
      "z1": 17132,
      "z2": 7033,
      "type": "us"
    },
    {
      "z1": 17288,
      "z2": 7024,
      "type": "us"
    },
    {
      "z1": 17289,
      "z2": 6994,
      "type": "us"
    },
    {
      "z1": 17338,
      "z2": 6816,
      "type": "us"
    },
    {
      "z1": 17415,
      "z2": 6733,
      "type": "us"
    },
    {
      "z1": 17476,
      "z2": 6665,
      "type": "us"
    },
    {
      "z1": 17507,
      "z2": 6630,
      "type": "us"
    },
    {
      "z1": 17617,
      "z2": 6502,
      "type": "us"
    },
    {
      "z1": 17739,
      "z2": 6356,
      "type": "us"
    },
    {
      "z1": 17767,
      "z2": 6321,
      "type": "us"
    },
    {
      "z1": 17793,
      "z2": 6289,
      "type": "us"
    },
    {
      "z1": 17819,
      "z2": 6257,
      "type": "us"
    },
    {
      "z1": 17924,
      "z2": 6123,
      "type": "us"
    },
    {
      "z1": 18092,
      "z2": 5899,
      "type": "us"
    },
    {
      "z1": 18206,
      "z2": 5891,
      "type": "us"
    },
    {
      "z1": 18207,
      "z2": 5861,
      "type": "us"
    },
    {
      "z1": 18236,
      "z2": 5694,
      "type": "us"
    },
    {
      "z1": 18286,
      "z2": 5622,
      "type": "us"
    },
    {
      "z1": 18367,
      "z2": 5499,
      "type": "us"
    },
    {
      "z1": 18433,
      "z2": 5397,
      "type": "us"
    },
    {
      "z1": 18479,
      "z2": 5324,
      "type": "us"
    },
    {
      "z1": 18502,
      "z2": 5287,
      "type": "us"
    },
    {
      "z1": 18660,
      "z2": 5285,
      "type": "us"
    },
    {
      "z1": 18662,
      "z2": 5173,
      "type": "us"
    },
    {
      "z1": 18663,
      "z2": 5143,
      "type": "us"
    },
    {
      "z1": 18674,
      "z2": 4999,
      "type": "us"
    },
    {
      "z1": 18692,
      "z2": 4968,
      "type": "us"
    },
    {
      "z1": 18762,
      "z2": 4967,
      "type": "us"
    },
    {
      "z1": 18773,
      "z2": 4946,
      "type": "us"
    },
    {
      "z1": 18807,
      "z2": 4912,
      "type": "us"
    },
    {
      "z1": 18808,
      "z2": 4882,
      "type": "us"
    },
    {
      "z1": 19056,
      "z2": 4830,
      "type": "us"
    },
    {
      "z1": 19061,
      "z2": 4744,
      "type": "us"
    },
    {
      "z1": 19063,
      "z2": 4702,
      "type": "us"
    },
    {
      "z1": 19072,
      "z2": 4489,
      "type": "us"
    },
    {
      "z1": 19074,
      "z2": 4377,
      "type": "us"
    },
    {
      "z1": 19075,
      "z2": 4347,
      "type": "us"
    },
    {
      "z1": 19099,
      "z2": 4322,
      "type": "us"
    },
    {
      "z1": 19100,
      "z2": 4169,
      "type": "us"
    },
    {
      "z1": 19149,
      "z2": 4061,
      "type": "us"
    },
    {
      "z1": 19153,
      "z2": 4051,
      "type": "us"
    },
    {
      "z1": 19180,
      "z2": 3989,
      "type": "us"
    },
    {
      "z1": 19240,
      "z2": 3970,
      "type": "us"
    },
    {
      "z1": 19285,
      "z2": 3886,
      "type": "us"
    },
    {
      "z1": 19286,
      "z2": 3856,
      "type": "us"
    },
    {
      "z1": 19296,
      "z2": 3710,
      "type": "us"
    },
    {
      "z1": 19368,
      "z2": 3672,
      "type": "us"
    },
    {
      "z1": 19369,
      "z2": 3642,
      "type": "us"
    },
    {
      "z1": 19403,
      "z2": 3576,
      "type": "us"
    },
    {
      "z1": 19404,
      "z2": 3546,
      "type": "us"
    },
    {
      "z1": 19415,
      "z2": 3394,
      "type": "us"
    },
    {
      "z1": 19455,
      "z2": 3279,
      "type": "us"
    },
    {
      "z1": 19497,
      "z2": 3276,
      "type": "us"
    },
    {
      "z1": 19522,
      "z2": 3227,
      "type": "us"
    },
    {
      "z1": 19523,
      "z2": 3197,
      "type": "us"
    },
    {
      "z1": 19530,
      "z2": 3176,
      "type": "us"
    },
    {
      "z1": 19549,
      "z2": 2992,
      "type": "us"
    },
    {
      "z1": 19598,
      "z2": 2828,
      "type": "us"
    },
    {
      "z1": 19649,
      "z2": 2799,
      "type": "us"
    },
    {
      "z1": 19650,
      "z2": 2769,
      "type": "us"
    },
    {
      "z1": 19652,
      "z2": 2636,
      "type": "us"
    },
    {
      "z1": 19717,
      "z2": 2387,
      "type": "us"
    },
    {
      "z1": 19748,
      "z2": 2377,
      "type": "us"
    },
    {
      "z1": 19768,
      "z2": 2314,
      "type": "us"
    },
    {
      "z1": 19769,
      "z2": 2284,
      "type": "us"
    },
    {
      "z1": 19771,
      "z2": 2151,
      "type": "us"
    },
    {
      "z1": 19802,
      "z2": 2005,
      "type": "us"
    },
    {
      "z1": 19874,
      "z2": 1604,
      "type": "us"
    },
    {
      "z1": 19875,
      "z2": 1597,
      "type": "us"
    },
    {
      "z1": 19900,
      "z2": 1436,
      "type": "us"
    },
    {
      "z1": 19936,
      "z2": 1389,
      "type": "us"
    },
    {
      "z1": 19938,
      "z2": 1277,
      "type": "us"
    },
    {
      "z1": 19939,
      "z2": 1247,
      "type": "us"
    },
    {
      "z1": 19946,
      "z2": 1198,
      "type": "us"
    },
    {
      "z1": 19947,
      "z2": 1168,
      "type": "us"
    },
    {
      "z1": 19948,
      "z2": 1039,
      "type": "us"
    },
    {
      "z1": 19962,
      "z2": 1022,
      "type": "us"
    },
    {
      "z1": 19963,
      "z2": 992,
      "type": "us"
    },
    {
      "z1": 19964,
      "z2": 865,
      "type": "us"
    },
    {
      "z1": 19973,
      "z2": 758,
      "type": "us"
    },
    {
      "z1": 19980,
      "z2": 655,
      "type": "us"
    },
    {
      "z1": 19985,
      "z2": 569,
      "type": "us"
    },
    {
      "z1": 19987,
      "z2": 527,
      "type": "us"
    },
    {
      "z1": 19996,
      "z2": 314,
      "type": "us"
    },
    {
      "z1": 19998,
      "z2": 202,
      "type": "us"
    },
    {
      "z1": 19999,
      "z2": 172,
      "type": "se"
    }
  ],
  "misc": {
    "min": [32, 172],
    "max": [19999, 20000],
    "width": [19967, 19828],
    "genSize": [
      97,
      100
    ]
  }
}
