{
  "version": "1.0",
  "contributionName": "Lyngesen24",
  "instanceName": "Lyngesen24-msp-2-50|50|50|50-uuuu-4_2",
  "objectives": 2,
  "objectiveType": ["int", "int"],
  "comments": "The nondominated sum for the MSP (points not stored for large Yn sizes)",
  "direction": ["min", "min"],
  "optimal": true,
  "valid": true,
  "card": 605,
  "suppCard": 5,
  "extCard": 5,
  "points": [
    {
      "z1": 1013,
      "z2": 39984,
      "type": "se"
    },
    {
      "z1": 1075,
      "z2": 39982,
      "type": "us"
    },
    {
      "z1": 1131,
      "z2": 39979,
      "type": "us"
    },
    {
      "z1": 1193,
      "z2": 39977,
      "type": "us"
    },
    {
      "z1": 1258,
      "z2": 39974,
      "type": "us"
    },
    {
      "z1": 1296,
      "z2": 39969,
      "type": "us"
    },
    {
      "z1": 1358,
      "z2": 39967,
      "type": "us"
    },
    {
      "z1": 1444,
      "z2": 39962,
      "type": "us"
    },
    {
      "z1": 1494,
      "z2": 39953,
      "type": "us"
    },
    {
      "z1": 1556,
      "z2": 39951,
      "type": "us"
    },
    {
      "z1": 1655,
      "z2": 39950,
      "type": "us"
    },
    {
      "z1": 1664,
      "z2": 39949,
      "type": "us"
    },
    {
      "z1": 1678,
      "z2": 39935,
      "type": "us"
    },
    {
      "z1": 1740,
      "z2": 39933,
      "type": "us"
    },
    {
      "z1": 1801,
      "z2": 39930,
      "type": "us"
    },
    {
      "z1": 1827,
      "z2": 39927,
      "type": "us"
    },
    {
      "z1": 1834,
      "z2": 39916,
      "type": "us"
    },
    {
      "z1": 1896,
      "z2": 39914,
      "type": "us"
    },
    {
      "z1": 2004,
      "z2": 39912,
      "type": "us"
    },
    {
      "z1": 2066,
      "z2": 39910,
      "type": "us"
    },
    {
      "z1": 2070,
      "z2": 39909,
      "type": "us"
    },
    {
      "z1": 2079,
      "z2": 39906,
      "type": "us"
    },
    {
      "z1": 2105,
      "z2": 39879,
      "type": "us"
    },
    {
      "z1": 2139,
      "z2": 39874,
      "type": "us"
    },
    {
      "z1": 2201,
      "z2": 39872,
      "type": "us"
    },
    {
      "z1": 2223,
      "z2": 39860,
      "type": "us"
    },
    {
      "z1": 2285,
      "z2": 39858,
      "type": "us"
    },
    {
      "z1": 2393,
      "z2": 39856,
      "type": "us"
    },
    {
      "z1": 2452,
      "z2": 39853,
      "type": "us"
    },
    {
      "z1": 2468,
      "z2": 39850,
      "type": "us"
    },
    {
      "z1": 2562,
      "z2": 39836,
      "type": "us"
    },
    {
      "z1": 2624,
      "z2": 39834,
      "type": "us"
    },
    {
      "z1": 2680,
      "z2": 39831,
      "type": "us"
    },
    {
      "z1": 2723,
      "z2": 39806,
      "type": "us"
    },
    {
      "z1": 2757,
      "z2": 39757,
      "type": "us"
    },
    {
      "z1": 2819,
      "z2": 39755,
      "type": "us"
    },
    {
      "z1": 2927,
      "z2": 39718,
      "type": "us"
    },
    {
      "z1": 2989,
      "z2": 39716,
      "type": "us"
    },
    {
      "z1": 3097,
      "z2": 39714,
      "type": "us"
    },
    {
      "z1": 3159,
      "z2": 39712,
      "type": "us"
    },
    {
      "z1": 3172,
      "z2": 39708,
      "type": "us"
    },
    {
      "z1": 3342,
      "z2": 39704,
      "type": "us"
    },
    {
      "z1": 3358,
      "z2": 39696,
      "type": "us"
    },
    {
      "z1": 3440,
      "z2": 39613,
      "type": "us"
    },
    {
      "z1": 3558,
      "z2": 39608,
      "type": "us"
    },
    {
      "z1": 3604,
      "z2": 39606,
      "type": "us"
    },
    {
      "z1": 3666,
      "z2": 39604,
      "type": "us"
    },
    {
      "z1": 3722,
      "z2": 39601,
      "type": "us"
    },
    {
      "z1": 3723,
      "z2": 39598,
      "type": "us"
    },
    {
      "z1": 3849,
      "z2": 39596,
      "type": "us"
    },
    {
      "z1": 3887,
      "z2": 39591,
      "type": "us"
    },
    {
      "z1": 3905,
      "z2": 39503,
      "type": "us"
    },
    {
      "z1": 3945,
      "z2": 39456,
      "type": "us"
    },
    {
      "z1": 4063,
      "z2": 39451,
      "type": "us"
    },
    {
      "z1": 4218,
      "z2": 39396,
      "type": "us"
    },
    {
      "z1": 4279,
      "z2": 39336,
      "type": "us"
    },
    {
      "z1": 4389,
      "z2": 39294,
      "type": "us"
    },
    {
      "z1": 4435,
      "z2": 39276,
      "type": "us"
    },
    {
      "z1": 4553,
      "z2": 39271,
      "type": "us"
    },
    {
      "z1": 4667,
      "z2": 39180,
      "type": "us"
    },
    {
      "z1": 4769,
      "z2": 39135,
      "type": "us"
    },
    {
      "z1": 4887,
      "z2": 39130,
      "type": "us"
    },
    {
      "z1": 4937,
      "z2": 39002,
      "type": "us"
    },
    {
      "z1": 4941,
      "z2": 39001,
      "type": "us"
    },
    {
      "z1": 4968,
      "z2": 38988,
      "type": "us"
    },
    {
      "z1": 5030,
      "z2": 38986,
      "type": "us"
    },
    {
      "z1": 5138,
      "z2": 38984,
      "type": "us"
    },
    {
      "z1": 5168,
      "z2": 38948,
      "type": "us"
    },
    {
      "z1": 5179,
      "z2": 38943,
      "type": "us"
    },
    {
      "z1": 5224,
      "z2": 38858,
      "type": "us"
    },
    {
      "z1": 5286,
      "z2": 38856,
      "type": "us"
    },
    {
      "z1": 5394,
      "z2": 38854,
      "type": "us"
    },
    {
      "z1": 5419,
      "z2": 38820,
      "type": "us"
    },
    {
      "z1": 5448,
      "z2": 38738,
      "type": "us"
    },
    {
      "z1": 5510,
      "z2": 38736,
      "type": "us"
    },
    {
      "z1": 5618,
      "z2": 38734,
      "type": "us"
    },
    {
      "z1": 5680,
      "z2": 38732,
      "type": "us"
    },
    {
      "z1": 5693,
      "z2": 38728,
      "type": "us"
    },
    {
      "z1": 5718,
      "z2": 38583,
      "type": "us"
    },
    {
      "z1": 5780,
      "z2": 38581,
      "type": "us"
    },
    {
      "z1": 5888,
      "z2": 38579,
      "type": "us"
    },
    {
      "z1": 5950,
      "z2": 38577,
      "type": "us"
    },
    {
      "z1": 5963,
      "z2": 38573,
      "type": "us"
    },
    {
      "z1": 6115,
      "z2": 38413,
      "type": "us"
    },
    {
      "z1": 6233,
      "z2": 38408,
      "type": "us"
    },
    {
      "z1": 6299,
      "z2": 38388,
      "type": "us"
    },
    {
      "z1": 6316,
      "z2": 38197,
      "type": "us"
    },
    {
      "z1": 6378,
      "z2": 38195,
      "type": "us"
    },
    {
      "z1": 6486,
      "z2": 38193,
      "type": "us"
    },
    {
      "z1": 6535,
      "z2": 38040,
      "type": "us"
    },
    {
      "z1": 6597,
      "z2": 38038,
      "type": "us"
    },
    {
      "z1": 6705,
      "z2": 38036,
      "type": "us"
    },
    {
      "z1": 6728,
      "z2": 37988,
      "type": "us"
    },
    {
      "z1": 6781,
      "z2": 37853,
      "type": "us"
    },
    {
      "z1": 6843,
      "z2": 37851,
      "type": "us"
    },
    {
      "z1": 6951,
      "z2": 37849,
      "type": "us"
    },
    {
      "z1": 6952,
      "z2": 37815,
      "type": "us"
    },
    {
      "z1": 7070,
      "z2": 37810,
      "type": "us"
    },
    {
      "z1": 7083,
      "z2": 37709,
      "type": "us"
    },
    {
      "z1": 7201,
      "z2": 37704,
      "type": "us"
    },
    {
      "z1": 7212,
      "z2": 37689,
      "type": "us"
    },
    {
      "z1": 7245,
      "z2": 37464,
      "type": "us"
    },
    {
      "z1": 7299,
      "z2": 37416,
      "type": "us"
    },
    {
      "z1": 7333,
      "z2": 37385,
      "type": "us"
    },
    {
      "z1": 7395,
      "z2": 37383,
      "type": "us"
    },
    {
      "z1": 7476,
      "z2": 37252,
      "type": "us"
    },
    {
      "z1": 7538,
      "z2": 37250,
      "type": "us"
    },
    {
      "z1": 7646,
      "z2": 37248,
      "type": "us"
    },
    {
      "z1": 7671,
      "z2": 37185,
      "type": "us"
    },
    {
      "z1": 7783,
      "z2": 37075,
      "type": "us"
    },
    {
      "z1": 7888,
      "z2": 36838,
      "type": "us"
    },
    {
      "z1": 7950,
      "z2": 36836,
      "type": "us"
    },
    {
      "z1": 7967,
      "z2": 36753,
      "type": "us"
    },
    {
      "z1": 8001,
      "z2": 36716,
      "type": "us"
    },
    {
      "z1": 8063,
      "z2": 36714,
      "type": "us"
    },
    {
      "z1": 8066,
      "z2": 36644,
      "type": "us"
    },
    {
      "z1": 8075,
      "z2": 36634,
      "type": "us"
    },
    {
      "z1": 8076,
      "z2": 36632,
      "type": "us"
    },
    {
      "z1": 8138,
      "z2": 36630,
      "type": "us"
    },
    {
      "z1": 8197,
      "z2": 36494,
      "type": "us"
    },
    {
      "z1": 8218,
      "z2": 36469,
      "type": "us"
    },
    {
      "z1": 8280,
      "z2": 36467,
      "type": "us"
    },
    {
      "z1": 8388,
      "z2": 36465,
      "type": "us"
    },
    {
      "z1": 8394,
      "z2": 36409,
      "type": "us"
    },
    {
      "z1": 8417,
      "z2": 36382,
      "type": "us"
    },
    {
      "z1": 8535,
      "z2": 36077,
      "type": "us"
    },
    {
      "z1": 8597,
      "z2": 36075,
      "type": "us"
    },
    {
      "z1": 8642,
      "z2": 35934,
      "type": "us"
    },
    {
      "z1": 8704,
      "z2": 35932,
      "type": "us"
    },
    {
      "z1": 8812,
      "z2": 35930,
      "type": "us"
    },
    {
      "z1": 8874,
      "z2": 35928,
      "type": "us"
    },
    {
      "z1": 8887,
      "z2": 35587,
      "type": "us"
    },
    {
      "z1": 8915,
      "z2": 35545,
      "type": "us"
    },
    {
      "z1": 8952,
      "z2": 35489,
      "type": "us"
    },
    {
      "z1": 9007,
      "z2": 35404,
      "type": "us"
    },
    {
      "z1": 9069,
      "z2": 35402,
      "type": "us"
    },
    {
      "z1": 9076,
      "z2": 35297,
      "type": "us"
    },
    {
      "z1": 9138,
      "z2": 35295,
      "type": "us"
    },
    {
      "z1": 9246,
      "z2": 35293,
      "type": "us"
    },
    {
      "z1": 9308,
      "z2": 35291,
      "type": "us"
    },
    {
      "z1": 9321,
      "z2": 35287,
      "type": "us"
    },
    {
      "z1": 9434,
      "z2": 34909,
      "type": "us"
    },
    {
      "z1": 9438,
      "z2": 34669,
      "type": "us"
    },
    {
      "z1": 9500,
      "z2": 34667,
      "type": "us"
    },
    {
      "z1": 9607,
      "z2": 34334,
      "type": "us"
    },
    {
      "z1": 9669,
      "z2": 34332,
      "type": "us"
    },
    {
      "z1": 9712,
      "z2": 34108,
      "type": "us"
    },
    {
      "z1": 9774,
      "z2": 34106,
      "type": "us"
    },
    {
      "z1": 9882,
      "z2": 34104,
      "type": "us"
    },
    {
      "z1": 9944,
      "z2": 34102,
      "type": "us"
    },
    {
      "z1": 9957,
      "z2": 34098,
      "type": "us"
    },
    {
      "z1": 9990,
      "z2": 33759,
      "type": "us"
    },
    {
      "z1": 10007,
      "z2": 33379,
      "type": "us"
    },
    {
      "z1": 10069,
      "z2": 33377,
      "type": "us"
    },
    {
      "z1": 10174,
      "z2": 33270,
      "type": "us"
    },
    {
      "z1": 10176,
      "z2": 32868,
      "type": "us"
    },
    {
      "z1": 10200,
      "z2": 32786,
      "type": "us"
    },
    {
      "z1": 10262,
      "z2": 32784,
      "type": "us"
    },
    {
      "z1": 10358,
      "z2": 32173,
      "type": "us"
    },
    {
      "z1": 10420,
      "z2": 32171,
      "type": "us"
    },
    {
      "z1": 10465,
      "z2": 31621,
      "type": "us"
    },
    {
      "z1": 10473,
      "z2": 31568,
      "type": "us"
    },
    {
      "z1": 10535,
      "z2": 31566,
      "type": "us"
    },
    {
      "z1": 10545,
      "z2": 31026,
      "type": "us"
    },
    {
      "z1": 10547,
      "z2": 31004,
      "type": "us"
    },
    {
      "z1": 10609,
      "z2": 31002,
      "type": "us"
    },
    {
      "z1": 10686,
      "z2": 30907,
      "type": "us"
    },
    {
      "z1": 10694,
      "z2": 30813,
      "type": "us"
    },
    {
      "z1": 10712,
      "z2": 30553,
      "type": "us"
    },
    {
      "z1": 10722,
      "z2": 30347,
      "type": "us"
    },
    {
      "z1": 10835,
      "z2": 30026,
      "type": "se"
    },
    {
      "z1": 10897,
      "z2": 30024,
      "type": "us"
    },
    {
      "z1": 10953,
      "z2": 30021,
      "type": "us"
    },
    {
      "z1": 11015,
      "z2": 30019,
      "type": "us"
    },
    {
      "z1": 11080,
      "z2": 30016,
      "type": "us"
    },
    {
      "z1": 11118,
      "z2": 30011,
      "type": "us"
    },
    {
      "z1": 11180,
      "z2": 30009,
      "type": "us"
    },
    {
      "z1": 11266,
      "z2": 30004,
      "type": "us"
    },
    {
      "z1": 11316,
      "z2": 29995,
      "type": "us"
    },
    {
      "z1": 11378,
      "z2": 29993,
      "type": "us"
    },
    {
      "z1": 11477,
      "z2": 29992,
      "type": "us"
    },
    {
      "z1": 11486,
      "z2": 29991,
      "type": "us"
    },
    {
      "z1": 11500,
      "z2": 29977,
      "type": "us"
    },
    {
      "z1": 11562,
      "z2": 29975,
      "type": "us"
    },
    {
      "z1": 11623,
      "z2": 29972,
      "type": "us"
    },
    {
      "z1": 11649,
      "z2": 29969,
      "type": "us"
    },
    {
      "z1": 11656,
      "z2": 29958,
      "type": "us"
    },
    {
      "z1": 11718,
      "z2": 29956,
      "type": "us"
    },
    {
      "z1": 11826,
      "z2": 29954,
      "type": "us"
    },
    {
      "z1": 11888,
      "z2": 29952,
      "type": "us"
    },
    {
      "z1": 11901,
      "z2": 29948,
      "type": "us"
    },
    {
      "z1": 11927,
      "z2": 29921,
      "type": "us"
    },
    {
      "z1": 11961,
      "z2": 29916,
      "type": "us"
    },
    {
      "z1": 12023,
      "z2": 29914,
      "type": "us"
    },
    {
      "z1": 12045,
      "z2": 29902,
      "type": "us"
    },
    {
      "z1": 12107,
      "z2": 29900,
      "type": "us"
    },
    {
      "z1": 12215,
      "z2": 29898,
      "type": "us"
    },
    {
      "z1": 12274,
      "z2": 29895,
      "type": "us"
    },
    {
      "z1": 12290,
      "z2": 29892,
      "type": "us"
    },
    {
      "z1": 12439,
      "z2": 29885,
      "type": "us"
    },
    {
      "z1": 12476,
      "z2": 29880,
      "type": "us"
    },
    {
      "z1": 12569,
      "z2": 29873,
      "type": "us"
    },
    {
      "z1": 12575,
      "z2": 29850,
      "type": "us"
    },
    {
      "z1": 12579,
      "z2": 29799,
      "type": "us"
    },
    {
      "z1": 12641,
      "z2": 29797,
      "type": "us"
    },
    {
      "z1": 12749,
      "z2": 29760,
      "type": "us"
    },
    {
      "z1": 12811,
      "z2": 29758,
      "type": "us"
    },
    {
      "z1": 12919,
      "z2": 29756,
      "type": "us"
    },
    {
      "z1": 12981,
      "z2": 29754,
      "type": "us"
    },
    {
      "z1": 12994,
      "z2": 29750,
      "type": "us"
    },
    {
      "z1": 13164,
      "z2": 29746,
      "type": "us"
    },
    {
      "z1": 13180,
      "z2": 29738,
      "type": "us"
    },
    {
      "z1": 13262,
      "z2": 29655,
      "type": "us"
    },
    {
      "z1": 13380,
      "z2": 29650,
      "type": "us"
    },
    {
      "z1": 13426,
      "z2": 29648,
      "type": "us"
    },
    {
      "z1": 13488,
      "z2": 29646,
      "type": "us"
    },
    {
      "z1": 13544,
      "z2": 29643,
      "type": "us"
    },
    {
      "z1": 13545,
      "z2": 29640,
      "type": "us"
    },
    {
      "z1": 13671,
      "z2": 29638,
      "type": "us"
    },
    {
      "z1": 13709,
      "z2": 29633,
      "type": "us"
    },
    {
      "z1": 13743,
      "z2": 29624,
      "type": "us"
    },
    {
      "z1": 13767,
      "z2": 29498,
      "type": "us"
    },
    {
      "z1": 13885,
      "z2": 29493,
      "type": "us"
    },
    {
      "z1": 14050,
      "z2": 29483,
      "type": "us"
    },
    {
      "z1": 14101,
      "z2": 29378,
      "type": "us"
    },
    {
      "z1": 14211,
      "z2": 29336,
      "type": "us"
    },
    {
      "z1": 14257,
      "z2": 29318,
      "type": "us"
    },
    {
      "z1": 14375,
      "z2": 29313,
      "type": "us"
    },
    {
      "z1": 14489,
      "z2": 29222,
      "type": "us"
    },
    {
      "z1": 14591,
      "z2": 29177,
      "type": "us"
    },
    {
      "z1": 14709,
      "z2": 29172,
      "type": "us"
    },
    {
      "z1": 14759,
      "z2": 29044,
      "type": "us"
    },
    {
      "z1": 14763,
      "z2": 29043,
      "type": "us"
    },
    {
      "z1": 14790,
      "z2": 29030,
      "type": "us"
    },
    {
      "z1": 14852,
      "z2": 29028,
      "type": "us"
    },
    {
      "z1": 14960,
      "z2": 29026,
      "type": "us"
    },
    {
      "z1": 14990,
      "z2": 28990,
      "type": "us"
    },
    {
      "z1": 15001,
      "z2": 28985,
      "type": "us"
    },
    {
      "z1": 15046,
      "z2": 28900,
      "type": "us"
    },
    {
      "z1": 15108,
      "z2": 28898,
      "type": "us"
    },
    {
      "z1": 15216,
      "z2": 28896,
      "type": "us"
    },
    {
      "z1": 15241,
      "z2": 28862,
      "type": "us"
    },
    {
      "z1": 15270,
      "z2": 28780,
      "type": "us"
    },
    {
      "z1": 15332,
      "z2": 28778,
      "type": "us"
    },
    {
      "z1": 15440,
      "z2": 28776,
      "type": "us"
    },
    {
      "z1": 15502,
      "z2": 28774,
      "type": "us"
    },
    {
      "z1": 15515,
      "z2": 28770,
      "type": "us"
    },
    {
      "z1": 15540,
      "z2": 28625,
      "type": "us"
    },
    {
      "z1": 15602,
      "z2": 28623,
      "type": "us"
    },
    {
      "z1": 15710,
      "z2": 28621,
      "type": "us"
    },
    {
      "z1": 15772,
      "z2": 28619,
      "type": "us"
    },
    {
      "z1": 15785,
      "z2": 28615,
      "type": "us"
    },
    {
      "z1": 15937,
      "z2": 28455,
      "type": "us"
    },
    {
      "z1": 16055,
      "z2": 28450,
      "type": "us"
    },
    {
      "z1": 16121,
      "z2": 28430,
      "type": "us"
    },
    {
      "z1": 16138,
      "z2": 28239,
      "type": "us"
    },
    {
      "z1": 16200,
      "z2": 28237,
      "type": "us"
    },
    {
      "z1": 16308,
      "z2": 28235,
      "type": "us"
    },
    {
      "z1": 16357,
      "z2": 28082,
      "type": "us"
    },
    {
      "z1": 16419,
      "z2": 28080,
      "type": "us"
    },
    {
      "z1": 16527,
      "z2": 28078,
      "type": "us"
    },
    {
      "z1": 16550,
      "z2": 28030,
      "type": "us"
    },
    {
      "z1": 16603,
      "z2": 27895,
      "type": "us"
    },
    {
      "z1": 16665,
      "z2": 27893,
      "type": "us"
    },
    {
      "z1": 16773,
      "z2": 27891,
      "type": "us"
    },
    {
      "z1": 16774,
      "z2": 27857,
      "type": "us"
    },
    {
      "z1": 16892,
      "z2": 27852,
      "type": "us"
    },
    {
      "z1": 16905,
      "z2": 27751,
      "type": "us"
    },
    {
      "z1": 17023,
      "z2": 27746,
      "type": "us"
    },
    {
      "z1": 17067,
      "z2": 27506,
      "type": "us"
    },
    {
      "z1": 17121,
      "z2": 27458,
      "type": "us"
    },
    {
      "z1": 17155,
      "z2": 27427,
      "type": "us"
    },
    {
      "z1": 17217,
      "z2": 27425,
      "type": "us"
    },
    {
      "z1": 17298,
      "z2": 27294,
      "type": "us"
    },
    {
      "z1": 17360,
      "z2": 27292,
      "type": "us"
    },
    {
      "z1": 17468,
      "z2": 27290,
      "type": "us"
    },
    {
      "z1": 17493,
      "z2": 27227,
      "type": "us"
    },
    {
      "z1": 17597,
      "z2": 27201,
      "type": "us"
    },
    {
      "z1": 17605,
      "z2": 27117,
      "type": "us"
    },
    {
      "z1": 17676,
      "z2": 27116,
      "type": "us"
    },
    {
      "z1": 17710,
      "z2": 26880,
      "type": "us"
    },
    {
      "z1": 17772,
      "z2": 26878,
      "type": "us"
    },
    {
      "z1": 17789,
      "z2": 26795,
      "type": "us"
    },
    {
      "z1": 17823,
      "z2": 26758,
      "type": "us"
    },
    {
      "z1": 17885,
      "z2": 26756,
      "type": "us"
    },
    {
      "z1": 17888,
      "z2": 26686,
      "type": "us"
    },
    {
      "z1": 17897,
      "z2": 26676,
      "type": "us"
    },
    {
      "z1": 17898,
      "z2": 26674,
      "type": "us"
    },
    {
      "z1": 17960,
      "z2": 26672,
      "type": "us"
    },
    {
      "z1": 18019,
      "z2": 26536,
      "type": "us"
    },
    {
      "z1": 18040,
      "z2": 26511,
      "type": "us"
    },
    {
      "z1": 18102,
      "z2": 26509,
      "type": "us"
    },
    {
      "z1": 18210,
      "z2": 26507,
      "type": "us"
    },
    {
      "z1": 18216,
      "z2": 26451,
      "type": "us"
    },
    {
      "z1": 18239,
      "z2": 26424,
      "type": "us"
    },
    {
      "z1": 18351,
      "z2": 26297,
      "type": "us"
    },
    {
      "z1": 18357,
      "z2": 26119,
      "type": "us"
    },
    {
      "z1": 18419,
      "z2": 26117,
      "type": "us"
    },
    {
      "z1": 18464,
      "z2": 25976,
      "type": "us"
    },
    {
      "z1": 18526,
      "z2": 25974,
      "type": "us"
    },
    {
      "z1": 18596,
      "z2": 25950,
      "type": "us"
    },
    {
      "z1": 18624,
      "z2": 25908,
      "type": "us"
    },
    {
      "z1": 18661,
      "z2": 25852,
      "type": "us"
    },
    {
      "z1": 18709,
      "z2": 25629,
      "type": "us"
    },
    {
      "z1": 18737,
      "z2": 25587,
      "type": "us"
    },
    {
      "z1": 18774,
      "z2": 25531,
      "type": "us"
    },
    {
      "z1": 18829,
      "z2": 25446,
      "type": "us"
    },
    {
      "z1": 18891,
      "z2": 25444,
      "type": "us"
    },
    {
      "z1": 18898,
      "z2": 25339,
      "type": "us"
    },
    {
      "z1": 18960,
      "z2": 25337,
      "type": "us"
    },
    {
      "z1": 19068,
      "z2": 25335,
      "type": "us"
    },
    {
      "z1": 19130,
      "z2": 25333,
      "type": "us"
    },
    {
      "z1": 19137,
      "z2": 25238,
      "type": "us"
    },
    {
      "z1": 19147,
      "z2": 25032,
      "type": "us"
    },
    {
      "z1": 19256,
      "z2": 24951,
      "type": "us"
    },
    {
      "z1": 19260,
      "z2": 24711,
      "type": "us"
    },
    {
      "z1": 19316,
      "z2": 24697,
      "type": "us"
    },
    {
      "z1": 19411,
      "z2": 24677,
      "type": "us"
    },
    {
      "z1": 19421,
      "z2": 24471,
      "type": "us"
    },
    {
      "z1": 19429,
      "z2": 24376,
      "type": "us"
    },
    {
      "z1": 19491,
      "z2": 24374,
      "type": "us"
    },
    {
      "z1": 19534,
      "z2": 24150,
      "type": "us"
    },
    {
      "z1": 19596,
      "z2": 24148,
      "type": "us"
    },
    {
      "z1": 19704,
      "z2": 24146,
      "type": "us"
    },
    {
      "z1": 19706,
      "z2": 23948,
      "type": "us"
    },
    {
      "z1": 19716,
      "z2": 23742,
      "type": "us"
    },
    {
      "z1": 19829,
      "z2": 23421,
      "type": "us"
    },
    {
      "z1": 19885,
      "z2": 23231,
      "type": "us"
    },
    {
      "z1": 19909,
      "z2": 23149,
      "type": "us"
    },
    {
      "z1": 19998,
      "z2": 22910,
      "type": "us"
    },
    {
      "z1": 20022,
      "z2": 22828,
      "type": "us"
    },
    {
      "z1": 20057,
      "z2": 22742,
      "type": "us"
    },
    {
      "z1": 20067,
      "z2": 22536,
      "type": "us"
    },
    {
      "z1": 20146,
      "z2": 22450,
      "type": "us"
    },
    {
      "z1": 20154,
      "z2": 22397,
      "type": "us"
    },
    {
      "z1": 20164,
      "z2": 22190,
      "type": "us"
    },
    {
      "z1": 20172,
      "z2": 22137,
      "type": "us"
    },
    {
      "z1": 20174,
      "z2": 21984,
      "type": "us"
    },
    {
      "z1": 20182,
      "z2": 21931,
      "type": "us"
    },
    {
      "z1": 20220,
      "z2": 21927,
      "type": "us"
    },
    {
      "z1": 20226,
      "z2": 21855,
      "type": "us"
    },
    {
      "z1": 20228,
      "z2": 21833,
      "type": "us"
    },
    {
      "z1": 20244,
      "z2": 21595,
      "type": "us"
    },
    {
      "z1": 20246,
      "z2": 21573,
      "type": "us"
    },
    {
      "z1": 20254,
      "z2": 21389,
      "type": "us"
    },
    {
      "z1": 20256,
      "z2": 21367,
      "type": "us"
    },
    {
      "z1": 20367,
      "z2": 21068,
      "type": "us"
    },
    {
      "z1": 20369,
      "z2": 21046,
      "type": "us"
    },
    {
      "z1": 20431,
      "z2": 21044,
      "type": "us"
    },
    {
      "z1": 20508,
      "z2": 20949,
      "type": "us"
    },
    {
      "z1": 20516,
      "z2": 20855,
      "type": "us"
    },
    {
      "z1": 20534,
      "z2": 20595,
      "type": "us"
    },
    {
      "z1": 20544,
      "z2": 20389,
      "type": "se"
    },
    {
      "z1": 20662,
      "z2": 20384,
      "type": "us"
    },
    {
      "z1": 20696,
      "z2": 20295,
      "type": "us"
    },
    {
      "z1": 20758,
      "z2": 20293,
      "type": "us"
    },
    {
      "z1": 20814,
      "z2": 20290,
      "type": "us"
    },
    {
      "z1": 20876,
      "z2": 20288,
      "type": "us"
    },
    {
      "z1": 20941,
      "z2": 20285,
      "type": "us"
    },
    {
      "z1": 20979,
      "z2": 20280,
      "type": "us"
    },
    {
      "z1": 21041,
      "z2": 20278,
      "type": "us"
    },
    {
      "z1": 21127,
      "z2": 20273,
      "type": "us"
    },
    {
      "z1": 21177,
      "z2": 20264,
      "type": "us"
    },
    {
      "z1": 21239,
      "z2": 20262,
      "type": "us"
    },
    {
      "z1": 21338,
      "z2": 20261,
      "type": "us"
    },
    {
      "z1": 21361,
      "z2": 20246,
      "type": "us"
    },
    {
      "z1": 21423,
      "z2": 20244,
      "type": "us"
    },
    {
      "z1": 21484,
      "z2": 20241,
      "type": "us"
    },
    {
      "z1": 21510,
      "z2": 20238,
      "type": "us"
    },
    {
      "z1": 21517,
      "z2": 20227,
      "type": "us"
    },
    {
      "z1": 21579,
      "z2": 20225,
      "type": "us"
    },
    {
      "z1": 21762,
      "z2": 20217,
      "type": "us"
    },
    {
      "z1": 21788,
      "z2": 20190,
      "type": "us"
    },
    {
      "z1": 21822,
      "z2": 20185,
      "type": "us"
    },
    {
      "z1": 21884,
      "z2": 20183,
      "type": "us"
    },
    {
      "z1": 21906,
      "z2": 20171,
      "type": "us"
    },
    {
      "z1": 21968,
      "z2": 20169,
      "type": "us"
    },
    {
      "z1": 22135,
      "z2": 20164,
      "type": "us"
    },
    {
      "z1": 22151,
      "z2": 20161,
      "type": "us"
    },
    {
      "z1": 22300,
      "z2": 20154,
      "type": "us"
    },
    {
      "z1": 22337,
      "z2": 20149,
      "type": "us"
    },
    {
      "z1": 22430,
      "z2": 20142,
      "type": "us"
    },
    {
      "z1": 22440,
      "z2": 20068,
      "type": "us"
    },
    {
      "z1": 22502,
      "z2": 20066,
      "type": "us"
    },
    {
      "z1": 22610,
      "z2": 20029,
      "type": "us"
    },
    {
      "z1": 22672,
      "z2": 20027,
      "type": "us"
    },
    {
      "z1": 22855,
      "z2": 20019,
      "type": "us"
    },
    {
      "z1": 23041,
      "z2": 20007,
      "type": "us"
    },
    {
      "z1": 23123,
      "z2": 19924,
      "type": "us"
    },
    {
      "z1": 23241,
      "z2": 19919,
      "type": "us"
    },
    {
      "z1": 23406,
      "z2": 19909,
      "type": "us"
    },
    {
      "z1": 23589,
      "z2": 19871,
      "type": "us"
    },
    {
      "z1": 23628,
      "z2": 19767,
      "type": "us"
    },
    {
      "z1": 23746,
      "z2": 19762,
      "type": "us"
    },
    {
      "z1": 23911,
      "z2": 19752,
      "type": "us"
    },
    {
      "z1": 23962,
      "z2": 19647,
      "type": "us"
    },
    {
      "z1": 24072,
      "z2": 19605,
      "type": "us"
    },
    {
      "z1": 24118,
      "z2": 19587,
      "type": "us"
    },
    {
      "z1": 24236,
      "z2": 19582,
      "type": "us"
    },
    {
      "z1": 24350,
      "z2": 19491,
      "type": "us"
    },
    {
      "z1": 24452,
      "z2": 19446,
      "type": "us"
    },
    {
      "z1": 24468,
      "z2": 19407,
      "type": "us"
    },
    {
      "z1": 24472,
      "z2": 19406,
      "type": "us"
    },
    {
      "z1": 24499,
      "z2": 19393,
      "type": "us"
    },
    {
      "z1": 24620,
      "z2": 19313,
      "type": "us"
    },
    {
      "z1": 24624,
      "z2": 19312,
      "type": "us"
    },
    {
      "z1": 24651,
      "z2": 19299,
      "type": "us"
    },
    {
      "z1": 24713,
      "z2": 19297,
      "type": "us"
    },
    {
      "z1": 24755,
      "z2": 19263,
      "type": "us"
    },
    {
      "z1": 24851,
      "z2": 19259,
      "type": "us"
    },
    {
      "z1": 24862,
      "z2": 19254,
      "type": "us"
    },
    {
      "z1": 24907,
      "z2": 19169,
      "type": "us"
    },
    {
      "z1": 24969,
      "z2": 19167,
      "type": "us"
    },
    {
      "z1": 24979,
      "z2": 19143,
      "type": "us"
    },
    {
      "z1": 25102,
      "z2": 19131,
      "type": "us"
    },
    {
      "z1": 25131,
      "z2": 19049,
      "type": "us"
    },
    {
      "z1": 25193,
      "z2": 19047,
      "type": "us"
    },
    {
      "z1": 25249,
      "z2": 18988,
      "type": "us"
    },
    {
      "z1": 25401,
      "z2": 18894,
      "type": "us"
    },
    {
      "z1": 25463,
      "z2": 18892,
      "type": "us"
    },
    {
      "z1": 25646,
      "z2": 18884,
      "type": "us"
    },
    {
      "z1": 25732,
      "z2": 18856,
      "type": "us"
    },
    {
      "z1": 25798,
      "z2": 18724,
      "type": "us"
    },
    {
      "z1": 25847,
      "z2": 18602,
      "type": "us"
    },
    {
      "z1": 25999,
      "z2": 18508,
      "type": "us"
    },
    {
      "z1": 26061,
      "z2": 18506,
      "type": "us"
    },
    {
      "z1": 26066,
      "z2": 18445,
      "type": "us"
    },
    {
      "z1": 26218,
      "z2": 18351,
      "type": "us"
    },
    {
      "z1": 26280,
      "z2": 18349,
      "type": "us"
    },
    {
      "z1": 26312,
      "z2": 18258,
      "type": "us"
    },
    {
      "z1": 26464,
      "z2": 18164,
      "type": "us"
    },
    {
      "z1": 26526,
      "z2": 18162,
      "type": "us"
    },
    {
      "z1": 26635,
      "z2": 18126,
      "type": "us"
    },
    {
      "z1": 26753,
      "z2": 18121,
      "type": "us"
    },
    {
      "z1": 26766,
      "z2": 18020,
      "type": "us"
    },
    {
      "z1": 26776,
      "z2": 17869,
      "type": "us"
    },
    {
      "z1": 26830,
      "z2": 17821,
      "type": "us"
    },
    {
      "z1": 26864,
      "z2": 17790,
      "type": "us"
    },
    {
      "z1": 26928,
      "z2": 17775,
      "type": "us"
    },
    {
      "z1": 26982,
      "z2": 17727,
      "type": "us"
    },
    {
      "z1": 27007,
      "z2": 17657,
      "type": "us"
    },
    {
      "z1": 27159,
      "z2": 17563,
      "type": "us"
    },
    {
      "z1": 27221,
      "z2": 17561,
      "type": "us"
    },
    {
      "z1": 27354,
      "z2": 17496,
      "type": "us"
    },
    {
      "z1": 27409,
      "z2": 17449,
      "type": "us"
    },
    {
      "z1": 27419,
      "z2": 17243,
      "type": "us"
    },
    {
      "z1": 27498,
      "z2": 17158,
      "type": "us"
    },
    {
      "z1": 27532,
      "z2": 17121,
      "type": "us"
    },
    {
      "z1": 27597,
      "z2": 17049,
      "type": "us"
    },
    {
      "z1": 27606,
      "z2": 17039,
      "type": "us"
    },
    {
      "z1": 27607,
      "z2": 17037,
      "type": "us"
    },
    {
      "z1": 27684,
      "z2": 17027,
      "type": "us"
    },
    {
      "z1": 27728,
      "z2": 16899,
      "type": "us"
    },
    {
      "z1": 27749,
      "z2": 16874,
      "type": "us"
    },
    {
      "z1": 27880,
      "z2": 16805,
      "type": "us"
    },
    {
      "z1": 27901,
      "z2": 16780,
      "type": "us"
    },
    {
      "z1": 27963,
      "z2": 16778,
      "type": "us"
    },
    {
      "z1": 28056,
      "z2": 16688,
      "type": "us"
    },
    {
      "z1": 28066,
      "z2": 16482,
      "type": "us"
    },
    {
      "z1": 28173,
      "z2": 16339,
      "type": "us"
    },
    {
      "z1": 28325,
      "z2": 16245,
      "type": "us"
    },
    {
      "z1": 28387,
      "z2": 16243,
      "type": "us"
    },
    {
      "z1": 28408,
      "z2": 16198,
      "type": "us"
    },
    {
      "z1": 28418,
      "z2": 15992,
      "type": "us"
    },
    {
      "z1": 28446,
      "z2": 15950,
      "type": "us"
    },
    {
      "z1": 28483,
      "z2": 15894,
      "type": "us"
    },
    {
      "z1": 28538,
      "z2": 15809,
      "type": "us"
    },
    {
      "z1": 28607,
      "z2": 15702,
      "type": "us"
    },
    {
      "z1": 28759,
      "z2": 15608,
      "type": "us"
    },
    {
      "z1": 28821,
      "z2": 15606,
      "type": "us"
    },
    {
      "z1": 28941,
      "z2": 15540,
      "type": "us"
    },
    {
      "z1": 28959,
      "z2": 15280,
      "type": "us"
    },
    {
      "z1": 28969,
      "z2": 15074,
      "type": "us"
    },
    {
      "z1": 29121,
      "z2": 14980,
      "type": "us"
    },
    {
      "z1": 29128,
      "z2": 14945,
      "type": "us"
    },
    {
      "z1": 29138,
      "z2": 14739,
      "type": "us"
    },
    {
      "z1": 29233,
      "z2": 14719,
      "type": "us"
    },
    {
      "z1": 29243,
      "z2": 14513,
      "type": "us"
    },
    {
      "z1": 29395,
      "z2": 14419,
      "type": "us"
    },
    {
      "z1": 29457,
      "z2": 14417,
      "type": "us"
    },
    {
      "z1": 29502,
      "z2": 14344,
      "type": "us"
    },
    {
      "z1": 29510,
      "z2": 14250,
      "type": "us"
    },
    {
      "z1": 29528,
      "z2": 13990,
      "type": "us"
    },
    {
      "z1": 29538,
      "z2": 13784,
      "type": "us"
    },
    {
      "z1": 29679,
      "z2": 13739,
      "type": "us"
    },
    {
      "z1": 29690,
      "z2": 13690,
      "type": "us"
    },
    {
      "z1": 29697,
      "z2": 13479,
      "type": "us"
    },
    {
      "z1": 29707,
      "z2": 13273,
      "type": "us"
    },
    {
      "z1": 29731,
      "z2": 13191,
      "type": "us"
    },
    {
      "z1": 29853,
      "z2": 13138,
      "type": "us"
    },
    {
      "z1": 29861,
      "z2": 13044,
      "type": "us"
    },
    {
      "z1": 29879,
      "z2": 12784,
      "type": "us"
    },
    {
      "z1": 29889,
      "z2": 12578,
      "type": "us"
    },
    {
      "z1": 29968,
      "z2": 12492,
      "type": "us"
    },
    {
      "z1": 29976,
      "z2": 12439,
      "type": "us"
    },
    {
      "z1": 29986,
      "z2": 12232,
      "type": "us"
    },
    {
      "z1": 29994,
      "z2": 12179,
      "type": "us"
    },
    {
      "z1": 29996,
      "z2": 12026,
      "type": "us"
    },
    {
      "z1": 30004,
      "z2": 11973,
      "type": "us"
    },
    {
      "z1": 30042,
      "z2": 11969,
      "type": "us"
    },
    {
      "z1": 30048,
      "z2": 11897,
      "type": "us"
    },
    {
      "z1": 30050,
      "z2": 11875,
      "type": "us"
    },
    {
      "z1": 30066,
      "z2": 11637,
      "type": "us"
    },
    {
      "z1": 30068,
      "z2": 11615,
      "type": "us"
    },
    {
      "z1": 30076,
      "z2": 11431,
      "type": "us"
    },
    {
      "z1": 30078,
      "z2": 11409,
      "type": "us"
    },
    {
      "z1": 30228,
      "z2": 11337,
      "type": "us"
    },
    {
      "z1": 30230,
      "z2": 11315,
      "type": "us"
    },
    {
      "z1": 30292,
      "z2": 11313,
      "type": "us"
    },
    {
      "z1": 30369,
      "z2": 11218,
      "type": "us"
    },
    {
      "z1": 30377,
      "z2": 11124,
      "type": "us"
    },
    {
      "z1": 30384,
      "z2": 11103,
      "type": "us"
    },
    {
      "z1": 30395,
      "z2": 10864,
      "type": "us"
    },
    {
      "z1": 30405,
      "z2": 10658,
      "type": "se"
    },
    {
      "z1": 30523,
      "z2": 10653,
      "type": "us"
    },
    {
      "z1": 30688,
      "z2": 10643,
      "type": "us"
    },
    {
      "z1": 30886,
      "z2": 10627,
      "type": "us"
    },
    {
      "z1": 31070,
      "z2": 10609,
      "type": "us"
    },
    {
      "z1": 31226,
      "z2": 10590,
      "type": "us"
    },
    {
      "z1": 31497,
      "z2": 10553,
      "type": "us"
    },
    {
      "z1": 31531,
      "z2": 10548,
      "type": "us"
    },
    {
      "z1": 31615,
      "z2": 10534,
      "type": "us"
    },
    {
      "z1": 32149,
      "z2": 10431,
      "type": "us"
    },
    {
      "z1": 32319,
      "z2": 10392,
      "type": "us"
    },
    {
      "z1": 34293,
      "z2": 10236,
      "type": "us"
    },
    {
      "z1": 34297,
      "z2": 10235,
      "type": "us"
    },
    {
      "z1": 34301,
      "z2": 10142,
      "type": "us"
    },
    {
      "z1": 34305,
      "z2": 10141,
      "type": "us"
    },
    {
      "z1": 34308,
      "z2": 10121,
      "type": "us"
    },
    {
      "z1": 34312,
      "z2": 10120,
      "type": "us"
    },
    {
      "z1": 34319,
      "z2": 9882,
      "type": "us"
    },
    {
      "z1": 34323,
      "z2": 9881,
      "type": "us"
    },
    {
      "z1": 34329,
      "z2": 9676,
      "type": "us"
    },
    {
      "z1": 34333,
      "z2": 9675,
      "type": "us"
    },
    {
      "z1": 34360,
      "z2": 9662,
      "type": "us"
    },
    {
      "z1": 34616,
      "z2": 9532,
      "type": "us"
    },
    {
      "z1": 34840,
      "z2": 9412,
      "type": "us"
    },
    {
      "z1": 35110,
      "z2": 9257,
      "type": "us"
    },
    {
      "z1": 35698,
      "z2": 9077,
      "type": "us"
    },
    {
      "z1": 35708,
      "z2": 8871,
      "type": "us"
    },
    {
      "z1": 35927,
      "z2": 8714,
      "type": "us"
    },
    {
      "z1": 36173,
      "z2": 8527,
      "type": "us"
    },
    {
      "z1": 36627,
      "z2": 8344,
      "type": "us"
    },
    {
      "z1": 36637,
      "z2": 8138,
      "type": "us"
    },
    {
      "z1": 36691,
      "z2": 8090,
      "type": "us"
    },
    {
      "z1": 36725,
      "z2": 8059,
      "type": "us"
    },
    {
      "z1": 36868,
      "z2": 7926,
      "type": "us"
    },
    {
      "z1": 37270,
      "z2": 7718,
      "type": "us"
    },
    {
      "z1": 37280,
      "z2": 7512,
      "type": "us"
    },
    {
      "z1": 37359,
      "z2": 7427,
      "type": "us"
    },
    {
      "z1": 37393,
      "z2": 7390,
      "type": "us"
    },
    {
      "z1": 37458,
      "z2": 7318,
      "type": "us"
    },
    {
      "z1": 37467,
      "z2": 7308,
      "type": "us"
    },
    {
      "z1": 37468,
      "z2": 7306,
      "type": "us"
    },
    {
      "z1": 37589,
      "z2": 7168,
      "type": "us"
    },
    {
      "z1": 37610,
      "z2": 7143,
      "type": "us"
    },
    {
      "z1": 37917,
      "z2": 6957,
      "type": "us"
    },
    {
      "z1": 37927,
      "z2": 6751,
      "type": "us"
    },
    {
      "z1": 38034,
      "z2": 6608,
      "type": "us"
    },
    {
      "z1": 38269,
      "z2": 6467,
      "type": "us"
    },
    {
      "z1": 38279,
      "z2": 6261,
      "type": "us"
    },
    {
      "z1": 38307,
      "z2": 6219,
      "type": "us"
    },
    {
      "z1": 38344,
      "z2": 6163,
      "type": "us"
    },
    {
      "z1": 38399,
      "z2": 6078,
      "type": "us"
    },
    {
      "z1": 38468,
      "z2": 5971,
      "type": "us"
    },
    {
      "z1": 38794,
      "z2": 5903,
      "type": "us"
    },
    {
      "z1": 38802,
      "z2": 5809,
      "type": "us"
    },
    {
      "z1": 38809,
      "z2": 5788,
      "type": "us"
    },
    {
      "z1": 38820,
      "z2": 5549,
      "type": "us"
    },
    {
      "z1": 38830,
      "z2": 5343,
      "type": "us"
    },
    {
      "z1": 38989,
      "z2": 5214,
      "type": "us"
    },
    {
      "z1": 38999,
      "z2": 5008,
      "type": "us"
    },
    {
      "z1": 39094,
      "z2": 4988,
      "type": "us"
    },
    {
      "z1": 39104,
      "z2": 4782,
      "type": "us"
    },
    {
      "z1": 39363,
      "z2": 4613,
      "type": "us"
    },
    {
      "z1": 39371,
      "z2": 4519,
      "type": "us"
    },
    {
      "z1": 39378,
      "z2": 4498,
      "type": "us"
    },
    {
      "z1": 39389,
      "z2": 4259,
      "type": "us"
    },
    {
      "z1": 39399,
      "z2": 4053,
      "type": "us"
    },
    {
      "z1": 39540,
      "z2": 4008,
      "type": "us"
    },
    {
      "z1": 39547,
      "z2": 3987,
      "type": "us"
    },
    {
      "z1": 39558,
      "z2": 3748,
      "type": "us"
    },
    {
      "z1": 39568,
      "z2": 3542,
      "type": "us"
    },
    {
      "z1": 39592,
      "z2": 3460,
      "type": "us"
    },
    {
      "z1": 39714,
      "z2": 3407,
      "type": "us"
    },
    {
      "z1": 39722,
      "z2": 3313,
      "type": "us"
    },
    {
      "z1": 39729,
      "z2": 3292,
      "type": "us"
    },
    {
      "z1": 39740,
      "z2": 3053,
      "type": "us"
    },
    {
      "z1": 39750,
      "z2": 2847,
      "type": "us"
    },
    {
      "z1": 39829,
      "z2": 2761,
      "type": "us"
    },
    {
      "z1": 39836,
      "z2": 2740,
      "type": "us"
    },
    {
      "z1": 39837,
      "z2": 2708,
      "type": "us"
    },
    {
      "z1": 39844,
      "z2": 2687,
      "type": "us"
    },
    {
      "z1": 39847,
      "z2": 2501,
      "type": "us"
    },
    {
      "z1": 39855,
      "z2": 2448,
      "type": "us"
    },
    {
      "z1": 39857,
      "z2": 2295,
      "type": "us"
    },
    {
      "z1": 39865,
      "z2": 2242,
      "type": "us"
    },
    {
      "z1": 39903,
      "z2": 2238,
      "type": "us"
    },
    {
      "z1": 39909,
      "z2": 2166,
      "type": "us"
    },
    {
      "z1": 39911,
      "z2": 2144,
      "type": "us"
    },
    {
      "z1": 39918,
      "z2": 2123,
      "type": "us"
    },
    {
      "z1": 39927,
      "z2": 1906,
      "type": "us"
    },
    {
      "z1": 39929,
      "z2": 1884,
      "type": "us"
    },
    {
      "z1": 39937,
      "z2": 1700,
      "type": "us"
    },
    {
      "z1": 39939,
      "z2": 1678,
      "type": "se"
    }
  ],
  "misc": {
    "min": [1013, 1678],
    "max": [39939, 39984],
    "width": [38926, 38306],
    "genSize": [
      33,
      50,
      9,
      8
    ]
  }
}
